potatohelper/FaceDetection.py
potatohelper/FaceMesh.py
potatohelper/FingerCounter.py
potatohelper/HandTrackingModule.py
potatohelper/TwoHandsFingerCounter.py
potatohelper/Utils.py
potatohelper/__init__.py
potatohelper-0.1.1.dist-info/METADATA
potatohelper-0.1.1.dist-info/WHEEL
potatohelper-0.1.1.dist-info/top_level.txt
potatohelper-0.1.1.dist-info/RECORD
