Metadata-Version: 2.1
Name: potatohelper
Version: 0.1.1
Summary: Just Nothing
Home-page: UNKNOWN
Author: Elon Musky
Author-email: kesore4222@yubua.com
License: UNKNOWN
Keywords: python,video,stream,opencv,opencv-python,cv,cv2
Platform: UNKNOWN
Classifier: Development Status :: 1 - Planning
Classifier: Intended Audience :: Developers
Classifier: Programming Language :: Python :: 3
Classifier: Operating System :: MacOS :: MacOS X
Classifier: Operating System :: Microsoft :: Windows
Requires-Dist: mediapipe
Requires-Dist: numpy
Requires-Dist: opencv-contrib-python
Requires-Dist: opencv-python
